PyOnsetT/.DS_Store
PyOnsetT/__init__.py
PyOnsetT/PyOnsetT.py
PyOnsetT/__main__.py
PyOnsetT-1.0.6.dist-info/RECORD
PyOnsetT-1.0.6.dist-info/metadata.json
PyOnsetT-1.0.6.dist-info/WHEEL
PyOnsetT-1.0.6.dist-info/entry_points.txt
PyOnsetT-1.0.6.dist-info/DESCRIPTION.rst
PyOnsetT-1.0.6.dist-info/top_level.txt
PyOnsetT-1.0.6.dist-info/METADATA
